chainercv2/__init__.py
chainercv2/model_provider.py
chainercv2/models/__init__.py
chainercv2/models/airnet.py
chainercv2/models/airnext.py
chainercv2/models/alexnet.py
chainercv2/models/alphapose_coco.py
chainercv2/models/bagnet.py
chainercv2/models/bamresnet.py
chainercv2/models/bisenet.py
chainercv2/models/bninception.py
chainercv2/models/cbamresnet.py
chainercv2/models/centernet.py
chainercv2/models/cgnet.py
chainercv2/models/channelnet.py
chainercv2/models/common.py
chainercv2/models/condensenet.py
chainercv2/models/dabnet.py
chainercv2/models/danet.py
chainercv2/models/darknet.py
chainercv2/models/darknet53.py
chainercv2/models/darts.py
chainercv2/models/deeplabv3.py
chainercv2/models/densenet.py
chainercv2/models/densenet_cifar.py
chainercv2/models/diapreresnet.py
chainercv2/models/diapreresnet_cifar.py
chainercv2/models/diaresnet.py
chainercv2/models/diaresnet_cifar.py
chainercv2/models/dicenet.py
chainercv2/models/diracnetv2.py
chainercv2/models/dla.py
chainercv2/models/dpn.py
chainercv2/models/drn.py
chainercv2/models/efficientnet.py
chainercv2/models/efficientnetedge.py
chainercv2/models/espnetv2.py
chainercv2/models/fastscnn.py
chainercv2/models/fastseresnet.py
chainercv2/models/fbnet.py
chainercv2/models/fcn8sd.py
chainercv2/models/fdmobilenet.py
chainercv2/models/fishnet.py
chainercv2/models/fpenet.py
chainercv2/models/ghostnet.py
chainercv2/models/hardnet.py
chainercv2/models/hrnet.py
chainercv2/models/ibppose_coco.py
chainercv2/models/icnet.py
chainercv2/models/igcv3.py
chainercv2/models/inceptionresnetv1.py
chainercv2/models/inceptionresnetv2.py
chainercv2/models/inceptionv3.py
chainercv2/models/inceptionv4.py
chainercv2/models/irevnet.py
chainercv2/models/jasper.py
chainercv2/models/jasperdr.py
chainercv2/models/lednet.py
chainercv2/models/lffd.py
chainercv2/models/lwopenpose_cmupan.py
chainercv2/models/menet.py
chainercv2/models/mixnet.py
chainercv2/models/mnasnet.py
chainercv2/models/mobilenet.py
chainercv2/models/mobilenet_cub.py
chainercv2-0.0.62.dist-info/LICENSE.txt
chainercv2-0.0.62.dist-info/METADATA
chainercv2-0.0.62.dist-info/WHEEL
chainercv2-0.0.62.dist-info/top_level.txt
chainercv2-0.0.62.dist-info/RECORD
